<?xml version="1.0" encoding="utf-8"?>
<IncrementalBankBuild Version="6" Flags="878078161">
	<Platform GUID="{235F85C3-8C71-406B-B036-48CA189076B0}">
		<Banks>
			<Language ID="393239870">
				<File Name="Init" Hash="427406614" Timestamp="1553742358"/>
				<File Name="Main" Hash="1109436229" Timestamp="1553742358"/>
			</Language>
		</Banks>
		<XMLInfo>
			<Language ID="-1">
				<File Name="" Hash="2157321416" Timestamp="1553742358"/>
			</Language>
		</XMLInfo>
	</Platform>
	<Platform GUID="{D0A82417-84AA-4512-A898-DB8B5B05C92A}">
		<Banks>
			<Language ID="393239870">
				<File Name="Init" Hash="605877604" Timestamp="1553742359"/>
				<File Name="Main" Hash="1109436229" Timestamp="1553742359"/>
			</Language>
		</Banks>
		<XMLInfo>
			<Language ID="-1">
				<File Name="" Hash="2373054646" Timestamp="1553742359"/>
			</Language>
		</XMLInfo>
	</Platform>
</IncrementalBankBuild>
